ehr/__init__.py
ehr/datasets/__init__.py
ehr/datasets/_base.py
ehr/datasets/dataset_profiler/__init__.py
ehr/datasets/dataset_profiler/pd_profiler.py
ehr/datasets/mimic/__init__.py
ehr/datasets/mimic/constants.py
ehr/datasets/mimic_ed/__init__.py
ehr/datasets/mimic_ed/constants.py
ehr/datasets/ohdsi/__init__.py
ehr/datasets/ohdsi/constants.py
ehr/features/__init__.py
ehr/features/feature_selector.py
ehr/utilities/__init__.py
ehr/utilities/_pandas.py
ehr/utilities/constants.py
ehr/utilities/fs.py
ehr/utilities/metadata.py
ehrnote-0.0.dev1.dist-info/LICENSE
ehrnote-0.0.dev1.dist-info/METADATA
ehrnote-0.0.dev1.dist-info/WHEEL
ehrnote-0.0.dev1.dist-info/top_level.txt
ehrnote-0.0.dev1.dist-info/RECORD
